codra/__init__.py
codra/lexer.py
codra/main.py
codra/parser.py
codra/parsetab.py
codra/symboltable.py
codra-0.0.3.dist-info/METADATA
codra-0.0.3.dist-info/WHEEL
codra-0.0.3.dist-info/top_level.txt
codra-0.0.3.dist-info/RECORD
