Metadata-Version: 2.1
Name: codra
Version: 0.0.3
Summary: A python template engine
Home-page: https://github.com/OmarElawady/codra
Author: Omar Elawady
Author-email: omarelawady1998@gmail.com
License: UNKNOWN
Platform: UNKNOWN
Classifier: Programming Language :: Python :: 3
Classifier: License :: OSI Approved :: MIT License
Classifier: Operating System :: OS Independent
Requires-Dist: ply
